Metadata-Version: 2.1
Name: odoo12-addon-geoengine-base-geolocalize
Version: 12.0.1.0.1
Summary: Geospatial support for base_geolocalize
Home-page: https://github.com/OCA/geospatial
Author: ACSONE SA/NV, Odoo Community Association (OCA)
Author-email: support@odoo-community.org
License: AGPL-3
Platform: UNKNOWN
Classifier: Programming Language :: Python
Classifier: Framework :: Odoo
Classifier: Framework :: Odoo :: 12.0
Classifier: License :: OSI Approved :: GNU Affero General Public License v3
Requires-Python: >=3.5
Requires-Dist: odoo12-addon-geoengine-partner
Requires-Dist: odoo (<12.1dev,>=12.0a)
Requires-Dist: requests
